pandoc_mcp_server/__init__.py
pandoc_mcp_server/server.py
pandoc_mcp_server-0.1.0.dist-info/licenses/LICENSE
pandoc_mcp_server-0.1.0.dist-info/METADATA
pandoc_mcp_server-0.1.0.dist-info/WHEEL
pandoc_mcp_server-0.1.0.dist-info/entry_points.txt
pandoc_mcp_server-0.1.0.dist-info/top_level.txt
pandoc_mcp_server-0.1.0.dist-info/RECORD
