Metadata-Version: 2.4
Name: pandoc-mcp-server
Version: 0.1.0
Summary: A Model Context Protocol server for Pandoc with optimized CJK typography support
Author-email: Rebirthli <bunny529eternal@gmail.com>
License: MIT
Project-URL: Homepage, https://github.com/Rebirthli/MCP
Project-URL: Repository, https://github.com/Rebirthli/MCP
Project-URL: Issues, https://github.com/Rebirthli/MCP/issues
Keywords: mcp,pandoc,document,conversion,markdown,pdf,cjk,chinese,japanese,korean
Classifier: Development Status :: 4 - Beta
Classifier: Intended Audience :: Developers
Classifier: License :: OSI Approved :: MIT License
Classifier: Programming Language :: Python :: 3
Classifier: Programming Language :: Python :: 3.10
Classifier: Programming Language :: Python :: 3.11
Classifier: Programming Language :: Python :: 3.12
Classifier: Topic :: Software Development :: Libraries
Classifier: Topic :: Text Processing :: Markup
Requires-Python: >=3.10
License-File: LICENSE
Requires-Dist: mcp>=1.0.0
Requires-Dist: pypandoc<2.0,>=1.11
Dynamic: license-file
